mcp_kyvos_server/__init__.py
mcp_kyvos_server/__main__.py
mcp_kyvos_server/exceptions.py
mcp_kyvos_server/server.py
mcp_kyvos_server/database/__init__.py
mcp_kyvos_server/database/db.py
mcp_kyvos_server/database/token_store.py
mcp_kyvos_server/kyvos/__init__.py
mcp_kyvos_server/kyvos/auth_config.py
mcp_kyvos_server/kyvos/client.py
mcp_kyvos_server/kyvos/config.py
mcp_kyvos_server/kyvos/fetcher.py
mcp_kyvos_server/kyvos/mcp_server_url.py
mcp_kyvos_server/kyvos/prompt/fsm_system_prompt.txt
mcp_kyvos_server/kyvos/prompt/kyvos_prompt.txt
mcp_kyvos_server/oauth/__init__.py
mcp_kyvos_server/oauth/routes/auth.py
mcp_kyvos_server/oauth/services/kyvos_services.py
mcp_kyvos_server/oauth/services/models.py
mcp_kyvos_server/oauth/services/oauth_client_authorization_service.py
mcp_kyvos_server/oauth/services/oauth_server_authorization_service.py
mcp_kyvos_server/oauth/templates/index.html
mcp_kyvos_server/utils/__init__.py
mcp_kyvos_server/utils/constants.py
mcp_kyvos_server/utils/io.py
mcp_kyvos_server/utils/logging.py
mcp_kyvos_server-1.1.0.dist-info/METADATA
mcp_kyvos_server-1.1.0.dist-info/WHEEL
mcp_kyvos_server-1.1.0.dist-info/entry_points.txt
mcp_kyvos_server-1.1.0.dist-info/RECORD
