Metadata-Version: 2.4
Name: mcp-kyvos-server
Version: 1.1.0
Summary: mcp-kyvos-server is a server implementation that integrates the Kyvos platform with the Model Context Protocol (MCP). It enables users to query Kyvos semantic models using natural language, translating prompts into executable queries and returning results from Kyvos. The server supports both SSE and STDIO communication modes and allows secure authentication using user-provided Kyvos credentials (basic and OAuth2.0).
Author-email: Kyvos <support@kyvos.io>
License: MIT License
Requires-Python: >=3.10
Requires-Dist: click>=8.1.7
Requires-Dist: colorlog>=6.9.0
Requires-Dist: fastapi>=0.115.12
Requires-Dist: httpx>=0.28.0
Requires-Dist: jinja2>=3.1.6
Requires-Dist: mcp>=1.9.1
Requires-Dist: peewee>=3.18.1
Requires-Dist: pydantic>=2.10.6
Requires-Dist: pyjwt>=2.10.1
Requires-Dist: python-dotenv>=1.0.1
Requires-Dist: python-jose>=3.4.0
Requires-Dist: requests-cache>=1.2.1
Requires-Dist: requests>=2.32.3
Requires-Dist: starlette>=0.37.1
Requires-Dist: trio>=0.29.0
Requires-Dist: truststore>=0.10.1
Requires-Dist: uvicorn>=0.27.1
